sentineltoolbox/__init__.py
sentineltoolbox/_utils.py
sentineltoolbox/api.py
sentineltoolbox/attributes.py
sentineltoolbox/configuration.py
sentineltoolbox/converters.py
sentineltoolbox/datatree_generator.py
sentineltoolbox/datatree_utils.py
sentineltoolbox/datatree_validator.py
sentineltoolbox/db.py
sentineltoolbox/env.py
sentineltoolbox/eopf_interface.py
sentineltoolbox/eopf_utils.py
sentineltoolbox/exceptions.py
sentineltoolbox/filesystem_utils.py
sentineltoolbox/flags.py
sentineltoolbox/hotfix.py
sentineltoolbox/ipynotebook.py
sentineltoolbox/logging_utils.py
sentineltoolbox/metadata_utils.py
sentineltoolbox/precision_utils.py
sentineltoolbox/proc_checkers.py
sentineltoolbox/product_type_utils.py
sentineltoolbox/raw_loaders.py
sentineltoolbox/sphinxenv.py
sentineltoolbox/stacutils.py
sentineltoolbox/templates.py
sentineltoolbox/typedefs.py
sentineltoolbox/warnings_utils.py
sentineltoolbox/xdatatree.py
sentineltoolbox/autodoc/__init__.py
sentineltoolbox/autodoc/constants.py
sentineltoolbox/autodoc/dataextractor.py
sentineltoolbox/autodoc/ellipsis.py
sentineltoolbox/autodoc/rendering.py
sentineltoolbox/autodoc/sphinx_post_build.py
sentineltoolbox/autodoc/sphinxenv.py
sentineltoolbox/conversion/S3__SL2FRP.py
sentineltoolbox/conversion/__init__.py
sentineltoolbox/conversion/common_s02msi.py
sentineltoolbox/conversion/convert.py
sentineltoolbox/conversion/convert_s02msi_l1ab_safe.py
sentineltoolbox/conversion/convert_s02msi_tile_safe.py
sentineltoolbox/conversion/convert_xml_tasktables.py
sentineltoolbox/conversion/converter_s03_adf_legacy.py
sentineltoolbox/conversion/eopf_extraction.py
sentineltoolbox/conversion/s2msi_l1ab_typedefs.py
sentineltoolbox/conversion/sentinel3.py
sentineltoolbox/conversion/utils.py
sentineltoolbox/conversion/conf/mappings/S1SEWRAW_mapping.json
sentineltoolbox/conversion/conf/mappings/S1SIWRAW_mapping.json
sentineltoolbox/conversion/conf/mappings/S1SSMRAW_mapping.json
sentineltoolbox/conversion/conf/mappings/S1SWVRAW_mapping.json
sentineltoolbox-0.6.4.dist-info/licenses/LICENSE
sentineltoolbox-0.6.4.dist-info/METADATA
sentineltoolbox-0.6.4.dist-info/WHEEL
sentineltoolbox-0.6.4.dist-info/entry_points.txt
sentineltoolbox-0.6.4.dist-info/top_level.txt
sentineltoolbox-0.6.4.dist-info/RECORD
