Metadata-Version: 2.4
Name: sentineltoolbox
Version: 0.6.4
Author: ACRI-ST
License:                                  Apache License
Classifier: License :: OSI Approved :: Apache Software License
Classifier: Programming Language :: Python :: 3 :: Only
Classifier: Programming Language :: Python :: 3.11
Classifier: Programming Language :: Python :: Implementation :: CPython
Classifier: Topic :: Scientific/Engineering
Classifier: Topic :: Software Development
Classifier: Typing :: Typed
Requires-Python: >=3.11
License-File: LICENSE
Requires-Dist: setuptools>=68.2.2
Requires-Dist: dask>=2023.11.0
Requires-Dist: distributed>=2023.11.0
Requires-Dist: xarray>=2024.11.0
Requires-Dist: numpy
Requires-Dist: zarr<3.0.0
Requires-Dist: fsspec[s3]>=2023.10.0
Requires-Dist: toml>=0.10.2
Requires-Dist: scipy
Requires-Dist: scikit-learn
Requires-Dist: tomli
Requires-Dist: colorlog
Requires-Dist: pandas
Requires-Dist: h5netcdf
Requires-Dist: eccodes>=1.7.1
Requires-Dist: ecmwflibs>=0.6.3
Requires-Dist: cfgrib>=0.9.10.4
Requires-Dist: geopandas
Requires-Dist: dacite
Requires-Dist: netcdf4>=1.6.5
Requires-Dist: rioxarray>=0.15.5
Requires-Dist: rasterio>=1.3.10
Requires-Dist: overrides
Requires-Dist: deepdiff
Requires-Dist: bs4
Requires-Dist: packaging
Requires-Dist: defusedxml
Requires-Dist: cql2
Provides-Extra: converter
Requires-Dist: eopf>=2.4.0; extra == "converter"
Provides-Extra: cluster-plugin
Requires-Dist: dask-jobqueue>=0.8.2; extra == "cluster-plugin"
Requires-Dist: dask-gateway>=2023.1.1; extra == "cluster-plugin"
Provides-Extra: tests
Requires-Dist: pytest<8; extra == "tests"
Requires-Dist: pytest-cov; extra == "tests"
Requires-Dist: hypothesis; extra == "tests"
Requires-Dist: pytest-error-for-skips; extra == "tests"
Requires-Dist: geopandas; extra == "tests"
Requires-Dist: dacite; extra == "tests"
Requires-Dist: lxml; extra == "tests"
Requires-Dist: jupytext; extra == "tests"
Requires-Dist: nbmake; extra == "tests"
Provides-Extra: linter
Requires-Dist: flake8; extra == "linter"
Provides-Extra: typing
Requires-Dist: mypy; extra == "typing"
Requires-Dist: types-python-dateutil; extra == "typing"
Requires-Dist: types-pytz; extra == "typing"
Requires-Dist: types-setuptools; extra == "typing"
Requires-Dist: types-toml; extra == "typing"
Requires-Dist: types-PyYAML; extra == "typing"
Requires-Dist: types-click; extra == "typing"
Requires-Dist: types-jinja2; extra == "typing"
Requires-Dist: types-colorama; extra == "typing"
Provides-Extra: formatter
Requires-Dist: black; extra == "formatter"
Requires-Dist: isort; extra == "formatter"
Provides-Extra: security
Requires-Dist: bandit; extra == "security"
Requires-Dist: safety; extra == "security"
Provides-Extra: notebook
Requires-Dist: jupyter>=1.0.0; extra == "notebook"
Requires-Dist: Jinja2>=3.1.2; extra == "notebook"
Requires-Dist: fonttools>=4.43.0; extra == "notebook"
Requires-Dist: matplotlib>=3.7.1; extra == "notebook"
Provides-Extra: doc
Requires-Dist: sphinx>=5.3.0; extra == "doc"
Requires-Dist: sphinx-autodoc-typehints>=1.22; extra == "doc"
Requires-Dist: sphinx_needs==5.1.0; extra == "doc"
Requires-Dist: jupyter-sphinx>=0.4.0; extra == "doc"
Requires-Dist: sphinx-book-theme>=1.0.1; extra == "doc"
Requires-Dist: sphinx-togglebutton>=0.3.2; extra == "doc"
Requires-Dist: sphinx-inline-tabs>=2023.4.21; extra == "doc"
Requires-Dist: sphinx-panels>=0.4.1; extra == "doc"
Requires-Dist: sphinx-test-reports==1.3.0; extra == "doc"
Requires-Dist: sqlalchemy>=2.0.0b1; extra == "doc"
Requires-Dist: myst-nb>=0.17.2; extra == "doc"
Requires-Dist: linkify-it-py>=2.0.0; extra == "doc"
Requires-Dist: numpydoc>=1.5.0; extra == "doc"
Requires-Dist: jupytext>=1.14.5; extra == "doc"
Requires-Dist: urllib3>=1.26.17; extra == "doc"
Requires-Dist: breathe>=4.35.0; extra == "doc"
Requires-Dist: sphinxcontrib-apidoc>=0.3.0; extra == "doc"
Requires-Dist: sphinxcontrib-spelling>=8.0.0; extra == "doc"
Requires-Dist: sphinxcontrib.plantuml; extra == "doc"
Requires-Dist: sphinxcontrib.mermaid; extra == "doc"
Requires-Dist: sphinx_copybutton>=0.5.2; extra == "doc"
Requires-Dist: GitPython>=3.1.41; extra == "doc"
Requires-Dist: nbsphinx>=0.9.1; extra == "doc"
Requires-Dist: mdutils>=1.6.0; extra == "doc"
Requires-Dist: tomark>=0.1.4; extra == "doc"
Requires-Dist: sphinxcontrib.mermaid; extra == "doc"
Provides-Extra: complexity
Requires-Dist: xenon>=0.9.1; extra == "complexity"
Provides-Extra: doc-cov
Requires-Dist: docstr-coverage>=2.2.0; extra == "doc-cov"
Provides-Extra: dev
Requires-Dist: pre-commit>=3.5.0; extra == "dev"
Requires-Dist: sentineltoolbox[complexity,doc-cov,tests]; extra == "dev"
Requires-Dist: sentineltoolbox[formatter,linter,typing]; extra == "dev"
Requires-Dist: sentineltoolbox[doc,notebook,security]; extra == "dev"
Requires-Dist: sentineltoolbox[cluster-plugin]; extra == "dev"
Requires-Dist: matplotlib; extra == "dev"
Dynamic: license-file
